WtwoBai.py
WtwoBai-0.1.0.dist-info/LICENSE
WtwoBai-0.1.0.dist-info/METADATA
WtwoBai-0.1.0.dist-info/WHEEL
WtwoBai-0.1.0.dist-info/top_level.txt
WtwoBai-0.1.0.dist-info/RECORD
